[
	{
		"coin": "GRLC",
        "servers": [
            {
                "geo": null,
                "urls": [
                    "grlc.suprnova.cc:8600"
                ]
            }
		],
		"miners": {
			"ccminer": {
				"ccurl": "stratum+tcp://%URL%",
				"ccalgo": "allium",
				"ccpass": "x",
				"ccuser": "%WAL%.%WORKER_NAME%"
			},
			"sgminer-gm": {
				"url": "stratum+tcp://%URL%",
				"algo": "allium",
				"pass": "x",
				"template": "%WAL%.%WORKER_NAME%",
				"user_config": "\"worksize\": \"64\"\n\"gpu-threads\": \"2\"\n\"intensity\": \"21\""
			}
		}
	},
	{
		"coin": "DCR",
        "servers": [
            {
                "geo": null,
                "urls": [
                    "dcr.suprnova.cc:3252"
                ]
            }
		],		
		"miners": {
			"ccminer": {
				"ccurl": "stratum+tcp://%URL%",
				"ccalgo": "decred",
				"ccpass": "x",
				"ccuser": "%WAL%.%WORKER_NAME%"
			},
			"sgminer-gm": {
				"url": "stratum+tcp://%URL%",
				"algo": "blake256r14",
				"pass": "x",
				"template": "%WAL%.%WORKER_NAME%",
				"user_config": "\"worksize\": \"64\"\n\"gpu-threads\": \"2\"\n\"intensity\": \"21\""
			},
			"claymore": {
                "dcri": "20",
                "dcoin": "dcr",
                "dpools_tpl": "POOL: %URL%, WALLET: %WAL%, WORKER: %WORKER_NAME%, PSW: x"
            }
		}
	},
	{
		"coin": "CHC",
		"servers": [
            {
                "geo": null,
                "urls": [
                    "chc.suprnova.cc:5888"
                ]
            }
		],
		"miners": {
			"ccminer": {
				"ccurl": "stratum+tcp://%URL%",
				"ccalgo": "c11",
				"ccpass": "x",
				"ccuser": "%WAL%.%WORKER_NAME%"
			},
			"sgminer-gm": {
				"url": "stratum+tcp://%URL%",
				"algo": "c11",
				"pass": "x",
				"template": "%WAL%.%WORKER_NAME%",
				"user_config": "\"worksize\": \"64\"\n\"gpu-threads\": \"2\"\n\"intensity\": \"21\""
			}
		}
	},
	{
		"coin": "ETN",
		"servers": [
            {
                "geo": null,
                "urls": [
                    "etn-stratum.suprnova.cc:8875"
                ]
            }
		],
		"miners": {
			"xmr-stak": {
				"url": "%URL%",
				"pass": "x",
				"template": "%WAL%.%WORKER_NAME%"
			},
			"claymore-x": {
				"xpools_tpl": "POOL: %URL%, WALLET: %WAL%.%WORKER_NAME%, PSW: x, ESM: 3, ALLPOOLS: 1"
			}
		}
	},
	{
		"coin": "BTG",
		"servers": [
            {
                "geo": null,
                "urls": [
                    "btg.suprnova.cc:8816"
                ]
            }
		],
		"miners": {
            "ewbf": {
                "algo": "144_5",
                "fork": "zhash",
                "zpass": "x",
                "zport": "%URL_PORT%",
                "zserver": "%URL_HOST%",
                "ztemplate": "%WAL%.%WORKER_NAME%",
                "user_config": "pers BgoldPoW"
            }
		}
	},
	{
		"coin": "BTCP",
		"servers": [
            {
                "geo": null,
                "urls": [
                    "btcp.suprnova.cc:6822"
                ]
            }
		],
		"miners": {
			"dstm": {
				"pass": "x",
				"port": "%URL_PORT%",
				"server": "%URL_HOST%",
				"template": "%WAL%.%WORKER_NAME%"
			},
			"ewbf": {
				"zpass": "x",
				"zport": "%URL_PORT%",
				"zserver": "%URL_HOST%",
				"ztemplate": "%WAL%.%WORKER_NAME%"
			},
			"bminer": {
				"url": "stratum+tcp://%URL%",
				"pass": "x",
				"template": "%WAL%.%WORKER_NAME%"
			},
			"claymore-z": {
				"zpools_tpl": "POOL: %URL%, WALLET: %WAL%.%WORKER_NAME%, PSW: x, ESM: 3, ALLPOOLS: 1"
			}
		}
	},
	{
		"coin": "ZCL",
		"servers": [
            {
                "geo": null,
                "urls": [
                    "zcl.suprnova.cc:4042"
                ]
            }
		],
		"miners": {
			"dstm": {
				"pass": "x",
				"port": "%URL_PORT%",
				"server": "%URL_HOST%",
				"template": "%WAL%.%WORKER_NAME%"
			},
			"ewbf": {
				"zpass": "x",
				"zport": "%URL_PORT%",
				"zserver": "%URL_HOST%",
				"ztemplate": "%WAL%.%WORKER_NAME%"
			},
			"bminer": {
				"url": "stratum+tcp://%URL%",
				"pass": "x",
				"template": "%WAL%.%WORKER_NAME%"
			},
			"claymore-z": {
				"zpools_tpl": "POOL: %URL%, WALLET: %WAL%.%WORKER_NAME%, PSW: x, ESM: 3, ALLPOOLS: 1"
			}
		}
	},
	{
		"coin": "ZEN",
		"servers": [
            {
                "geo": null,
                "urls": [
                    "zen.suprnova.cc:3618"
                ]
            }
		],
		"miners": {
			"dstm": {
				"pass": "x",
				"port": "%URL_PORT%",
				"server": "%URL_HOST%",
				"template": "%WAL%.%WORKER_NAME%"
			},
			"ewbf": {
				"zpass": "x",
				"zport": "%URL_PORT%",
				"zserver": "%URL_HOST%",
				"ztemplate": "%WAL%.%WORKER_NAME%"
			},
			"bminer": {
				"url": "stratum+tcp://%URL%",
				"pass": "x",
				"template": "%WAL%.%WORKER_NAME%"
			},
			"claymore-z": {
				"zpools_tpl": "POOL: %URL%, WALLET: %WAL%.%WORKER_NAME%, PSW: x, ESM: 3, ALLPOOLS: 1"
			}
		}
	},
	{
		"coin": "ZEC",
		"servers": [
            {
                "geo": null,
                "urls": [
                    "zec-eu.suprnova.cc:2142"
                ]
            }
		],
		"miners": {
			"dstm": {
				"pass": "x",
				"port": "%URL_PORT%",
				"server": "%URL_HOST%",
				"template": "%WAL%.%WORKER_NAME%"
			},
			"ewbf": {
				"zpass": "x",
				"zport": "%URL_PORT%",
				"zserver": "%URL_HOST%",
				"ztemplate": "%WAL%.%WORKER_NAME%"
			},
			"bminer": {
				"url": "stratum+tcp://%URL%",
				"pass": "x",
				"template": "%WAL%.%WORKER_NAME%"
			},
			"claymore-z": {
				"zpools_tpl": "POOL: %URL%, WALLET: %WAL%.%WORKER_NAME%, PSW: x, ESM: 3, ALLPOOLS: 1"
			}
		}
	},
	{
		"coin": "BTCZ",
		"servers": [
            {
                "geo": null,
                "urls": [
                    "btcz.suprnova.cc:5586"
                ]
            }
		],
		"miners": {
			"ewbf": {
                "algo": "144_5",
                "fork": "zhash",
                "zpass": "x",
                "zport": "%URL_PORT%",
                "zserver": "%URL_HOST%",
                "ztemplate": "%WAL%.%WORKER_NAME%",
                "user_config": "pers BitcoinZ"
            }
		}
	},
	{
		"coin": "KMD",
		"servers": [
            {
                "geo": null,
                "urls": [
                    "kmd.suprnova.cc:6250"
                ]
            }
		],
		"miners": {
			"dstm": {
				"pass": "x",
				"port": "%URL_PORT%",
				"server": "%URL_HOST%",
				"template": "%WAL%.%WORKER_NAME%"
			},
			"ewbf": {
				"zpass": "x",
				"zport": "%URL_PORT%",
				"zserver": "%URL_HOST%",
				"ztemplate": "%WAL%.%WORKER_NAME%"
			},
			"bminer": {
				"url": "stratum+tcp://%URL%",
				"pass": "x",
				"template": "%WAL%.%WORKER_NAME%"
			},
			"claymore-z": {
				"zpools_tpl": "POOL: %URL%, WALLET: %WAL%.%WORKER_NAME%, PSW: x, ESM: 3, ALLPOOLS: 1"
			}
		}
	},
	{
		"coin": "HUSH",
		"servers": [
            {
                "geo": null,
                "urls": [
                    "hush.suprnova.cc:4048"
                ]
            }
		],
		"miners": {
			"dstm": {
				"pass": "x",
				"port": "%URL_PORT%",
				"server": "%URL_HOST%",
				"template": "%WAL%.%WORKER_NAME%"
			},
			"ewbf": {
				"zpass": "x",
				"zport": "%URL_PORT%",
				"zserver": "%URL_HOST%",
				"ztemplate": "%WAL%.%WORKER_NAME%"
			},
			"bminer": {
				"url": "stratum+tcp://%URL%",
				"pass": "x",
				"template": "%WAL%.%WORKER_NAME%"
			},
			"claymore-z": {
				"zpools_tpl": "POOL: %URL%, WALLET: %WAL%.%WORKER_NAME%, PSW: x, ESM: 3, ALLPOOLS: 1"
			}
		}
	},
	{
		"coin": "GRS",
		"servers": [
            {
                "geo": null,
                "urls": [
                    "grs.suprnova.cc:5544"
                ]
            }
		],
		"miners": {
			"ccminer": {
				"ccurl": "stratum+tcp://%URL%",
				"ccalgo": "groestl",
				"ccpass": "x",
				"ccuser": "%WAL%.%WORKER_NAME%"
			},
			"sgminer-gm": {
				"url": "stratum+tcp://%URL%",
				"algo": "groestlcoin",
				"pass": "x",
				"template": "%DWAL.%WORKER_NAME% PSW: x",
				"user_config": "\"worksize\": \"64\"\n\"gpu-threads\": \"2\"\n\"intensity\": \"21\""
			}
		}
	},
	{
		"coin": "ETH",
		"servers": [
            {
                "geo": null,
                "urls": [
                    ""
                ]
            }
		],
		"miners": {
			"claymore": {
				"epools_tpl": "POOL: eth.suprnova.cc:5005, WALLET: %WAL%.%WORKER_NAME%, PSW: x"
			},
			"ethminer": {
				"cuda": 1,
				"pass": "x",
				"port": "5005",
				"server": "eth.suprnova.cc",
				"template": "%WAL%.%WORKER_NAME%",
				"user_config": "--stratum-protocol 1"
			},
			"sgminer-gm": {
				"url": "stratum+tcp://eth.suprnova.cc:5005",
				"algo": "ethash",
				"pass": "x",
				"template": "%WAL%.%WORKER_NAME%",
				"user_config": "\"worksize\": \"192\"\n\"gpu-threads\": \"1\"\n\"xintensity\": \"1024\""
			}
		}
	},
	{
		"coin": "UBIQ",
		"servers": [
            {
                "geo": null,
                "urls": [
                    ""
                ]
            }
		],
		"miners": {
			"claymore": {
				"epools_tpl": "POOL: ubiq.suprnova.cc:3030, WALLET: %WAL%.%WORKER_NAME%, PSW: x"
			},
			"ethminer": {
				"cuda": 1,
				"pass": "x",
				"port": "3030",
				"server": "ubiq.suprnova.cc",
				"template": "%WAL%.%WORKER_NAME%",
				"user_config": "--stratum-protocol 1"
			},
			"sgminer-gm": {
				"url": "stratum+tcp://ubiq.suprnova.cc:3030",
				"algo": "ethash",
				"pass": "x",
				"template": "%WAL%.%WORKER_NAME%",
				"user_config": "\"worksize\": \"192\"\n\"gpu-threads\": \"1\"\n\"xintensity\": \"1024\""
			}
		}
	},
	{
		"coin": "LBRY",
		"servers": [
            {
                "geo": null,
                "urls": [
                    ""
                ]
            }
		],
		"miners": {
			"ccminer": {
				"ccurl": "stratum+tcp://lbry.suprnova.cc:6256",
				"ccalgo": "lbry",
				"ccpass": "x",
				"ccuser": "%WAL%.%WORKER_NAME%"
			},
			"sgminer-gm": {
				"url": "stratum+tcp://lbry.suprnova.cc:6256",
				"algo": "lbry",
				"pass": "x",
				"template": "%WAL%.%WORKER_NAME%",
				"user_config": "\"worksize\": \"64\"\n\"gpu-threads\": \"2\"\n\"intensity\": \"21\""
			}
		}
	},
	{
		"coin": "XVG-lyra2rev2",
		"servers": [
            {
                "geo": null,
                "urls": [
                    ""
                ]
            }
		],
		"miners": {
			"sgminer-gm": {
				"url": "stratum+tcp://xvg-lyra.suprnova.cc:2595",
				"algo": "lyra2rev2",
				"pass": "x",
				"template": "%WAL%.%WORKER_NAME%",
				"user_config": "\"rawintensity\" : \"5120\"\n\"worksize\" : \"256\"\n\"lookup-gap\" : \"2\"\n\"thread-concurrency\" : \"8192\"\n\"shaders\" : \"0\"\n\"gpu-threads\" : \"2\""
			},
			"ccminer": {
				"ccurl": "stratum+tcp://xvg-lyra.suprnova.cc:2595",
				"ccalgo": "lyra2rev2",
				"ccpass": "x",
				"ccuser": "%WAL%.%WORKER_NAME%"
			}
		}
	},
	{
		"coin": "VTC",
		"servers": [
            {
                "geo": null,
                "urls": [
                    ""
                ]
            }
		],
		"miners": {
			"sgminer-gm": {
				"url": "stratum+tcp://vtc.suprnova.cc:5678",
				"algo": "lyra2rev2",
				"pass": "x",
				"template": "%WAL%.%WORKER_NAME%",
				"user_config": "\"rawintensity\" : \"5120\"\n\"worksize\" : \"256\"\n\"lookup-gap\" : \"2\"\n\"thread-concurrency\" : \"8192\"\n\"shaders\" : \"0\"\n\"gpu-threads\" : \"2\""
			},
			"ccminer": {
				"ccurl": "stratum+tcp://vtc.suprnova.cc:5678",
				"ccalgo": "lyra2rev2",
				"ccpass": "x",
				"ccuser": "%WAL%.%WORKER_NAME%"
			}
		},
		"coins": ["VTC"]
	},
	{
		"coin": "RACE",
		"servers": [
            {
                "geo": null,
                "urls": [
                    ""
                ]
            }
		],
		"miners": {
			"sgminer-gm": {
				"url": "stratum+tcp://race.suprnova.cc:5650",
				"algo": "lyra2rev2",
				"pass": "x",
				"template": "%WAL%.%WORKER_NAME%",
				"user_config": "\"rawintensity\" : \"5120\"\n\"worksize\" : \"256\"\n\"lookup-gap\" : \"2\"\n\"thread-concurrency\" : \"8192\"\n\"shaders\" : \"0\"\n\"gpu-threads\" : \"2\""
			},
			"ccminer": {
				"ccurl": "stratum+tcp://race.suprnova.cc:5650",
				"ccalgo": "lyra2rev2",
				"ccpass": "x",
				"ccuser": "%WAL%.%WORKER_NAME%"
			}
		}
	},
	{
		"coin": "KREDS",
		"servers": [
            {
                "geo": null,
                "urls": [
                    ""
                ]
            }
		],
		"miners": {
			"sgminer-gm": {
				"url": "stratum+tcp://kreds.suprnova.cc:7196",
				"algo": "lyra2rev2",
				"pass": "x",
				"template": "%WAL%.%WORKER_NAME%",
				"user_config": "\"rawintensity\" : \"5120\"\n\"worksize\" : \"256\"\n\"lookup-gap\" : \"2\"\n\"thread-concurrency\" : \"8192\"\n\"shaders\" : \"0\"\n\"gpu-threads\" : \"2\""
			},
			"ccminer": {
				"ccurl": "stratum+tcp://kreds.suprnova.cc:7196",
				"ccalgo": "lyra2rev2",
				"ccpass": "x",
				"ccuser": "%WAL%.%WORKER_NAME%"
			}
		}
	},
	{
		"coin": "STAK",
		"servers": [
            {
                "geo": null,
                "urls": [
                    ""
                ]
            }
		],
		"miners": {
			"sgminer-gm": {
				"url": "stratum+tcp://stak.suprnova.cc:7706",
				"algo": "lyra2rev2",
				"pass": "x",
				"template": "%WAL%.%WORKER_NAME%",
				"user_config": "\"rawintensity\" : \"5120\"\n\"worksize\" : \"256\"\n\"lookup-gap\" : \"2\"\n\"thread-concurrency\" : \"8192\"\n\"shaders\" : \"0\"\n\"gpu-threads\" : \"2\""
			},
			"ccminer": {
				"ccurl": "stratum+tcp://stak.suprnova.cc:7706",
				"ccalgo": "lyra2rev2",
				"ccpass": "x",
				"ccuser": "%WAL%.%WORKER_NAME%"
			}
		}
	},
	{
		"coin": "MONA",
		"servers": [
            {
                "geo": null,
                "urls": [
                    ""
                ]
            }
		],
		"miners": {
			"sgminer-gm": {
				"url": "stratum+tcp://mona.suprnova.cc:2995",
				"algo": "lyra2rev2",
				"pass": "x",
				"template": "%WAL%.%WORKER_NAME%",
				"user_config": "\"rawintensity\" : \"5120\"\n\"worksize\" : \"256\"\n\"lookup-gap\" : \"2\"\n\"thread-concurrency\" : \"8192\"\n\"shaders\" : \"0\"\n\"gpu-threads\" : \"2\""
			},
			"ccminer": {
				"ccurl": "stratum+tcp://mona.suprnova.cc:2995",
				"ccalgo": "lyra2rev2",
				"ccpass": "x",
				"ccuser": "%WAL%.%WORKER_NAME%"
			}
		}
	},
	{
		"coin": "CRS",
		"servers": [
            {
                "geo": null,
                "urls": [
                    ""
                ]
            }
		],
		"miners": {
			"sgminer-gm": {
				"url": "stratum+tcp://crs.suprnova.cc:4155",
				"algo": "lyra2z",
				"pass": "x",
				"template": "%WAL%.%WORKER_NAME%",
				"user_config": "\"rawintensity\" : \"5120\"\n\"worksize\" : \"256\"\n\"lookup-gap\" : \"2\"\n\"thread-concurrency\" : \"8192\"\n\"shaders\" : \"0\"\n\"gpu-threads\" : \"2\""
			},
			"ccminer": {
				"ccurl": "stratum+tcp://crs.suprnova.cc:4155",
				"ccalgo": "lyra2z",
				"ccpass": "x",
				"ccuser": "%WAL%.%WORKER_NAME%"
			}
		}
	},
	{
		"coin": "XZC",
		"servers": [
            {
                "geo": null,
                "urls": [
                    ""
                ]
            }
		],
		"miners": {
			"sgminer-gm": {
				"url": "stratum+tcp://xzc.suprnova.cc:1569",
				"algo": "lyra2z",
				"pass": "x",
				"template": "%WAL%.%WORKER_NAME%",
				"user_config": "\"rawintensity\" : \"5120\"\n\"worksize\" : \"256\"\n\"lookup-gap\" : \"2\"\n\"thread-concurrency\" : \"8192\"\n\"shaders\" : \"0\"\n\"gpu-threads\" : \"2\""
			},
			"ccminer": {
				"ccurl": "stratum+tcp://xzc.suprnova.cc:1569",
				"ccalgo": "lyra2z",
				"ccpass": "x",
				"ccuser": "%WAL%.%WORKER_NAME%"
			}
		}
	},
	{
		"coin": "DGB-groestl",
		"servers": [
            {
                "geo": null,
                "urls": [
                    ""
                ]
            }
		],
		"miners": {
			"sgminer-gm": {
				"url": "stratum+tcp://dgbg.suprnova.cc:7978",
				"algo": "myriadcoin-groestl",
				"pass": "x",
				"template": "%WAL%.%WORKER_NAME%",
				"user_config": "\"rawintensity\" : \"5120\"\n\"worksize\" : \"256\"\n\"lookup-gap\" : \"2\"\n\"thread-concurrency\" : \"8192\"\n\"shaders\" : \"0\"\n\"gpu-threads\" : \"2\""
			},
			"ccminer": {
				"ccurl": "stratum+tcp://dgbg.suprnova.cc:7978",
				"ccalgo": "myr-gr",
				"ccpass": "x",
				"ccuser": "%WAL%.%WORKER_NAME%"
			}
		}
	},
	{
		"coin": "POLY",
		"servers": [
            {
                "geo": null,
                "urls": [
                    ""
                ]
            }
		],
		"miners": {
			"sgminer-gm": {
				"url": "stratum+tcp://poly.suprnova.cc:7935",
				"algo": "polytimos",
				"pass": "x",
				"template": "%WAL%.%WORKER_NAME%",
				"user_config": "\"rawintensity\" : \"5120\"\n\"worksize\" : \"256\"\n\"lookup-gap\" : \"2\"\n\"thread-concurrency\" : \"8192\"\n\"shaders\" : \"0\"\n\"gpu-threads\" : \"2\""
			},
			"ccminer": {
				"ccurl": "stratum+tcp://poly.suprnova.cc:7935",
				"ccalgo": "polytimos",
				"ccpass": "x",
				"ccuser": "%WAL%.%WORKER_NAME%"
			}
		}
	},
	{
		"coin": "DGB-qubit",
		"servers": [
            {
                "geo": null,
                "urls": [
                    ""
                ]
            }
		],
		"miners": {
			"sgminer-gm": {
				"url": "stratum+tcp://dgbq.suprnova.cc:8531",
				"algo": "qubitcoin",
				"pass": "x",
				"template": "%WAL%.%WORKER_NAME%",
				"user_config": "\"rawintensity\" : \"5120\"\n\"worksize\" : \"256\"\n\"lookup-gap\" : \"2\"\n\"thread-concurrency\" : \"8192\"\n\"shaders\" : \"0\"\n\"gpu-threads\" : \"2\""
			},
			"ccminer": {
				"ccurl": "stratum+tcp://dgbq.suprnova.cc:8531",
				"ccalgo": "qubit",
				"ccpass": "x",
				"ccuser": "%WAL%.%WORKER_NAME%"
			}
		}
	},
	{
		"coin": "EMC2",
		"servers": [
            {
                "geo": null,
                "urls": [
                    ""
                ]
            }
		],
		"miners": {
			"ccminer": {
				"ccurl": "stratum+tcp://emc2.suprnova.cc:3366",
				"ccalgo": "scrypt",
				"ccpass": "x",
				"ccuser": "%WAL%.%WORKER_NAME%"
			},
			"sgminer-gm": {
				"url": "stratum+tcp://emc2.suprnova.cc:3366",
				"algo": "scrypt",
				"pass": "x",
				"template": "%WAL%.%WORKER_NAME%",
				"user_config": "\"worksize\": \"64\"\n\"gpu-threads\": \"2\"\n\"intensity\": \"21\""
			}
		}
	},
	{
		"coin": "GMC",
		"servers": [
            {
                "geo": null,
                "urls": [
                    ""
                ]
            }
		],
		"miners": {
			"ccminer": {
				"ccurl": "stratum+tcp://gmc.suprnova.cc:7351",
				"ccalgo": "scrypt",
				"ccpass": "x",
				"ccuser": "%WAL%.%WORKER_NAME%"
			},
			"sgminer-gm": {
				"url": "stratum+tcp://gmc.suprnova.cc:7351",
				"algo": "scrypt",
				"pass": "x",
				"template": "%WAL%.%WORKER_NAME%",
				"user_config": "\"worksize\": \"64\"\n\"gpu-threads\": \"2\"\n\"intensity\": \"21\""
			}
		}
	},
	{
		"coin": "FLO",
		"servers": [
            {
                "geo": null,
                "urls": [
                    ""
                ]
            }
		],
		"miners": {
			"ccminer": {
				"ccurl": "stratum+tcp://flo.suprnova.cc:3210",
				"ccalgo": "scrypt",
				"ccpass": "x",
				"ccuser": "%WAL%.%WORKER_NAME%"
			},
			"sgminer-gm": {
				"url": "stratum+tcp://flo.suprnova.cc:3210",
				"algo": "scrypt",
				"pass": "x",
				"template": "%WAL%.%WORKER_NAME%",
				"user_config": "\"worksize\": \"64\"\n\"gpu-threads\": \"2\"\n\"intensity\": \"21\""
			}
		}
	},
	{
		"coin": "LTC",
		"servers": [
            {
                "geo": null,
                "urls": [
                    ""
                ]
            }
		],
		"miners": {
			"ccminer": {
				"ccurl": "stratum+tcp://ltc.suprnova.cc:4444",
				"ccalgo": "scrypt",
				"ccpass": "x",
				"ccuser": "%WAL%.%WORKER_NAME%"
			},
			"sgminer-gm": {
				"url": "stratum+tcp://ltc.suprnova.cc:4444",
				"algo": "scrypt",
				"pass": "x",
				"template": "%WAL%.%WORKER_NAME%",
				"user_config": "\"worksize\": \"64\"\n\"gpu-threads\": \"2\"\n\"intensity\": \"21\""
			}
		}
	},
	{
		"coin": "BCH",
		"servers": [
            {
                "geo": null,
                "urls": [
                    ""
                ]
            }
		],
		"miners": {
			"ccminer": {
				"ccurl": "stratum+tcp://bch.suprnova.cc:3333",
				"ccalgo": "sha256d",
				"ccpass": "x",
				"ccuser": "%WAL%.%WORKER_NAME%"
			},
			"sgminer-gm": {
				"url": "stratum+tcp://bch.suprnova.cc:3333",
				"algo": "sha256d",
				"pass": "x",
				"template": "%WAL%.%WORKER_NAME%",
				"user_config": "\"worksize\": \"64\"\n\"gpu-threads\": \"2\"\n\"intensity\": \"21\""
			}
		}
	},
	{
		"coin": "LCC",
		"servers": [
            {
                "geo": null,
                "urls": [
                    ""
                ]
            }
		],
		"miners": {
			"ccminer": {
				"ccurl": "stratum+tcp://lcc.suprnova.cc:6868",
				"ccalgo": "sha256d",
				"ccpass": "x",
				"ccuser": "%WAL%.%WORKER_NAME%"
			},
			"sgminer-gm": {
				"url": "stratum+tcp://lcc.suprnova.cc:6868",
				"algo": "sha256d",
				"pass": "x",
				"template": "%WAL%.%WORKER_NAME%",
				"user_config": "\"worksize\": \"64\"\n\"gpu-threads\": \"2\"\n\"intensity\": \"21\""
			}
		}
	},
	{
		"coin": "DGB-skein",
		"servers": [
            {
                "geo": null,
                "urls": [
                    ""
                ]
            }
		],
		"miners": {
			"ccminer": {
				"ccurl": "stratum+tcp://dgbs.suprnova.cc:5226",
				"ccalgo": "skein",
				"ccpass": "x",
				"ccuser": "%WAL%.%WORKER_NAME%"
			},
			"sgminer-gm": {
				"url": "stratum+tcp://dgbs.suprnova.cc:5226",
				"algo": "skein",
				"pass": "x",
				"template": "%WAL%.%WORKER_NAME%",
				"user_config": "\"worksize\": \"64\"\n\"gpu-threads\": \"2\"\n\"intensity\": \"21\""
			}
		}
	},
	{
		"coin": "MUN",
		"servers": [
            {
                "geo": null,
                "urls": [
                    ""
                ]
            }
		],
		"miners": {
			"ccminer": {
				"ccurl": "stratum+tcp://mun.suprnova.cc:8963",
				"ccalgo": "skunk",
				"ccpass": "x",
				"ccuser": "%WAL%.%WORKER_NAME%"
			},
			"sgminer-gm": {
				"url": "stratum+tcp://mun.suprnova.cc:8963",
				"algo": "skunk",
				"pass": "x",
				"template": "%WAL%.%WORKER_NAME%",
				"user_config": "\"worksize\": \"64\"\n\"gpu-threads\": \"2\"\n\"intensity\": \"21\""
			}
		},
		"coins": ["MUN"]
	},
	{
		"coin": "BTX",
		"servers": [
            {
                "geo": null,
                "urls": [
                    ""
                ]
            }
		],
		"miners": {
			"ccminer": {
				"ccurl": "stratum+tcp://btx.suprnova.cc:3629",
				"ccalgo": "bitcore",
				"ccpass": "x",
				"ccuser": "%WAL%.%WORKER_NAME%"
			},
			"sgminer-gm": {
				"url": "stratum+tcp://btx.suprnova.cc:3629",
				"algo": "timetravel10",
				"pass": "x",
				"template": "%WAL%.%WORKER_NAME%",
				"user_config": "\"worksize\": \"64\"\n\"gpu-threads\": \"2\"\n\"intensity\": \"21\""
			}
		},
		"coins": ["MUN"]
	},
	{
		"coin": "DASH",
		"servers": [
            {
                "geo": null,
                "urls": [
                    ""
                ]
            }
		],
		"miners": {
			"ccminer": {
				"ccurl": "stratum+tcp://dash.suprnova.cc:9991",
				"ccalgo": "x11",
				"ccpass": "x",
				"ccuser": "%WAL%.%WORKER_NAME%"
			},
			"sgminer-gm": {
				"url": "stratum+tcp://dash.suprnova.cc:9991",
				"algo": "darkcoin",
				"pass": "x",
				"template": "%WAL%.%WORKER_NAME%,",
				"user_config": "\"worksize\": \"64\"\n\"gpu-threads\": \"2\"\n\"intensity\": \"21\""
			}
		}
	},
	{
		"coin": "START",
		"servers": [
            {
                "geo": null,
                "urls": [
                    ""
                ]
            }
		],
		"miners": {
			"ccminer": {
				"ccurl": "stratum+tcp://start.suprnova.cc:2207",
				"ccalgo": "x11",
				"ccpass": "x",
				"ccuser": "%WAL%.%WORKER_NAME%"
			},
			"sgminer-gm": {
				"url": "stratum+tcp://start.suprnova.cc:2207",
				"algo": "darkcoin",
				"pass": "x",
				"template": "%WAL%.%WORKER_NAME%,",
				"user_config": "\"worksize\": \"64\"\n\"gpu-threads\": \"2\"\n\"intensity\": \"21\""
			}
		}
	},
	{
		"coin": "SIB",
		"servers": [
            {
                "geo": null,
                "urls": [
                    ""
                ]
            }
		],
		"miners": {
			"ccminer": {
				"ccurl": "stratum+tcp://sib.suprnova.cc:3458",
				"ccalgo": "sib",
				"ccpass": "x",
				"ccuser": "%WAL%.%WORKER_NAME%"
			},
			"sgminer-gm": {
				"url": "stratum+tcp://sib.suprnova.cc:3458",
				"algo": "sibcoin",
				"pass": "x",
				"template": "%WAL%.%WORKER_NAME%",
				"user_config": "\"worksize\": \"64\"\n\"gpu-threads\": \"2\"\n\"intensity\": \"21\"
			}
		}
	},
	{
		"coin": "RVN",
		"servers": [
            {
                "geo": null,
                "urls": [
                    ""
                ]
            }
		],
		"miners": {
			"ccminer": {
				"ccurl": "stratum+tcp://rvn.suprnova.cc:6667",
				"ccalgo": "x16r",
				"ccpass": "x",
				"ccuser": "%WAL%.%WORKER_NAME%"
			},
			"sgminer-gm": {
				"url": "stratum+tcp://rvn.suprnova.cc:6667",
				"algo": "x16r",
				"pass": "x",
				"template": "%WAL%.%WORKER_NAME%",
				"user_config": "\"worksize\": \"64\"\n\"gpu-threads\": \"2\"\n\"intensity\": \"21\""
			}
		}
	},
	{
		"coin": "XVG-x17",
		"miners": {
			"ccminer": {
				"ccurl": "stratum+tcp://xvg-x17.suprnova.cc:7477",
				"ccalgo": "x17",
				"ccpass": "x",
				"ccuser": "%WAL%.%WORKER_NAME%"
			},
			"sgminer-gm": {
				"url": "stratum+tcp://xvg-x17.suprnova.cc:7477",
				"algo": "x17",
				"pass": "x",
				"template": "%WAL%.%WORKER_NAME%",
				"user_config": "\"worksize\": \"64\"\n\"gpu-threads\": \"2\"\n\"intensity\": \"21\""
			}
		}
	},
	{
		"coin": "BSD",
		"miners": {
			"ccminer": {
				"ccurl": "stratum+tcp://bsd.suprnova.cc:8686",
				"ccalgo": "xevan",
				"ccpass": "x",
				"ccuser": "%WAL%.%WORKER_NAME%"
			},
			"sgminer-gm": {
				"url": "stratum+tcp://bsd.suprnova.cc:8686",
				"algo": "xevan",
				"pass": "x",
				"template": "%WAL%.%WORKER_NAME%",
				"user_config": "\"worksize\": \"64\"\n\"gpu-threads\": \"2\"\n\"intensity\": \"21\""
			}
		}
	},
	{
		"coin": "WAVI",
		"servers": [
            {
                "geo": null,
                "urls": [
                    ""
                ]
            }
		],
		"miners": {
			"ccminer": {
				"ccurl": "stratum+tcp://wavi.suprnova.cc:6762",
				"ccalgo": "yescrypt32",
				"ccpass": "x",
				"ccuser": "%WAL%.%WORKER_NAME%"
			},
			"sgminer-gm": {
				"url": "stratum+tcp://wavi.suprnova.cc:6762",
				"algo": "yescrypt32",
				"pass": "x",
				"template": "%WAL%.%WORKER_NAME%",
				"user_config": "\"worksize\": \"64\"\n\"gpu-threads\": \"2\"\n\"intensity\": \"21\""
			}
		}
	}
]